snowd/__init__.py
snowd/__main__.py
snowd/client.py
snowd/envvars.py
snowd/git.py
snowd/polling.py
snowd/state.py
snowd/utils.py
snowd-0.1.3.dist-info/METADATA
snowd-0.1.3.dist-info/WHEEL
snowd-0.1.3.dist-info/RECORD
