Metadata-Version: 2.1
Name: snowd
Version: 0.1.3
Summary: 
Author: David Gallay
Author-email: david.gallay@nagra.com
Requires-Python: >=3.9.0,<4.0.0
Classifier: Programming Language :: Python :: 3
Classifier: Programming Language :: Python :: 3.9
Classifier: Programming Language :: Python :: 3.10
Classifier: Programming Language :: Python :: 3.11
Classifier: Programming Language :: Python :: 3.12
Requires-Dist: gitpython (>=3.1.40,<4.0.0)
Requires-Dist: nagra-network-misc-utils (==0.2.2)
Requires-Dist: pydantic (>=2.5.2,<3.0.0)
Requires-Dist: pysnow (>=0.7.17,<0.8.0)
Requires-Dist: pyyaml (>=6.0.1,<7.0.0)
